flask_autorest/__init__.py
flask_autorest/autorest.py
flask_autorest/constants.py
flask_autorest/utils.py
flask_autorest/views.py
flask_autorest-0.1.6.dist-info/LICENSE
flask_autorest-0.1.6.dist-info/METADATA
flask_autorest-0.1.6.dist-info/WHEEL
flask_autorest-0.1.6.dist-info/top_level.txt
flask_autorest-0.1.6.dist-info/RECORD
