Metadata-Version: 2.1
Name: flask-autorest
Version: 0.1.6
Summary: auto create restful apis for database, with the help of dataset.
Home-page: https://github.com/dantezhu/flask_autorest
Author: dantezhu
Author-email: dantezhu <zny2008@gmail.com>
License: MIT
Project-URL: Homepage, https://github.com/dantezhu/flask_autorest
Platform: any
License-File: LICENSE
Requires-Dist: flask
Requires-Dist: dataset
